[
    {
        "id": "assassin",
        "name": "Assassin"
    },
    {
        "id": "barbarian",
        "name": "Barbarian"
    },
    {
        "id": "bard",
        "name": "Bard"
    },
    {
        "id": "blackguard",
        "name": "Blackguard",
        "is_prestige": true
    },
    {
        "id": "cleric",
        "name": "Cleric"
    },
    {
        "id": "druid",
        "name": "Druid"
    },
    {
        "id": "fighter",
        "name": "Fighter"
    },
    {
        "id": "justice-of-weald-and-woe",
        "name": "Justice of Weald and Woe",
        "is_prestige": true,
        "prerequisites": [
            {
                "type": "minimum base attack bonus",
                "values": [6]
            },
            {
                "type": "skill",
                "values": [
                    { "value": "craft", "skill_ranks": 8, "craft_type": "bowmaking" },
                    { "value": "hide", "skill_ranks": 8 },
                    { "value": "knowledge", "skill_ranks": 4 },
                    { "value": "stealth", "skill_ranks": 8 },
                    { "value": "survival", "skill_ranks": 8 }
                ]
            },
            {
                "type": "feat",
                "values": [
                    "point-blank-shot",
                    { "value": "weapon-focus", "weapon_focus_type": "longbow" }
                ]
            }
        ],
        "references": [
            {
                "source": "champions-of-ruin",
                "page_from": 48,
                "page_to": 53
            }
        ]
    },
    {
        "id": "ranger",
        "name": "Ranger"
    },
    {
        "id": "rogue",
        "name": "Rogue"
    },
    {
        "id": "sorcerer",
        "name": "Sorcerer"
    },
    {
        "id": "wizard",
        "name": "Wizard"
    }
]
